african_knowledge_ai/__init__.py
african_knowledge_ai/client.py
african_knowledge_ai/exceptions.py
african_knowledge_ai/utils.py
tests/__init__.py
tests/test_client.py
african_knowledge_ai-0.1.0.dist-info/LICENSE
african_knowledge_ai-0.1.0.dist-info/METADATA
african_knowledge_ai-0.1.0.dist-info/WHEEL
african_knowledge_ai-0.1.0.dist-info/top_level.txt
african_knowledge_ai-0.1.0.dist-info/RECORD
